fontsearch/__init__.py
fontsearch/cli.py
fontsearch/core.py
fontsearch/gui.py
fontsearch/gui_advanced.py
fontsearch/gui_i18n.py
fontsearch/widget.py
fontsearch/i18n/__init__.py
fontsearch/i18n/translations/ar.json
fontsearch/i18n/translations/bn.json
fontsearch/i18n/translations/en.json
fontsearch/i18n/translations/es.json
fontsearch/i18n/translations/fr.json
fontsearch/i18n/translations/hi.json
fontsearch/i18n/translations/ja.json
fontsearch/i18n/translations/pt.json
fontsearch/i18n/translations/ru.json
fontsearch/i18n/translations/zh.json
fontsearch-1.1.1.dist-info/licenses/LICENSE
fontsearch-1.1.1.dist-info/METADATA
fontsearch-1.1.1.dist-info/WHEEL
fontsearch-1.1.1.dist-info/entry_points.txt
fontsearch-1.1.1.dist-info/top_level.txt
fontsearch-1.1.1.dist-info/RECORD
