Metadata-Version: 2.4
Name: fontsearch
Version: 1.1.1
Summary: Cross-platform font discovery and analysis library
Home-page: https://github.com/datamoc/fontsearch
Author: Michel Weinachter
Author-email: Michel Weinachter <michel.weinachter@example.com>
License: LGPL-3.0-or-later
Project-URL: Homepage, https://github.com/datamoc/fontsearch
Project-URL: Repository, https://github.com/datamoc/fontsearch
Project-URL: Documentation, https://github.com/datamoc/fontsearch/blob/main/README.md
Project-URL: Bug Reports, https://github.com/datamoc/fontsearch/issues
Classifier: Development Status :: 5 - Production/Stable
Classifier: Intended Audience :: Developers
Classifier: License :: OSI Approved :: GNU Lesser General Public License v3 (LGPLv3)
Classifier: Operating System :: OS Independent
Classifier: Programming Language :: Python :: 3
Classifier: Programming Language :: Python :: 3.8
Classifier: Programming Language :: Python :: 3.9
Classifier: Programming Language :: Python :: 3.10
Classifier: Programming Language :: Python :: 3.11
Classifier: Programming Language :: Python :: 3.12
Classifier: Topic :: Multimedia :: Graphics
Classifier: Topic :: Software Development :: Libraries :: Python Modules
Classifier: Topic :: System :: Systems Administration
Classifier: Topic :: Text Processing :: Fonts
Requires-Python: >=3.8
License-File: LICENSE
Provides-Extra: full
Requires-Dist: fonttools>=4.0.0; extra == "full"
Provides-Extra: gui
Requires-Dist: pillow>=8.0.0; extra == "gui"
Provides-Extra: all
Requires-Dist: fonttools>=4.0.0; extra == "all"
Requires-Dist: pillow>=8.0.0; extra == "all"
Provides-Extra: dev
Requires-Dist: pytest>=6.0.0; extra == "dev"
Requires-Dist: pytest-cov>=2.0.0; extra == "dev"
Requires-Dist: black>=21.0.0; extra == "dev"
Requires-Dist: flake8>=3.8.0; extra == "dev"
Requires-Dist: mypy>=0.800; extra == "dev"
Dynamic: author
Dynamic: home-page
Dynamic: license-file
Dynamic: requires-python
